[{"name":"Hidden Valley","countries":"United States","regions":"Idaho","difficulty":"easy","color":"green","gladed":null,"grooming":null,"inclined_length_m":560,"descent_m":58,"ascent_m":1,"average_pitch_%":0.11,"max_pitch_%":0.25,"min_elevation_m":1813,"max_elevation_m":1871,"difficulty_convention":"north_america","openskimap":"https://openskimap.org/?obj=04552efafcc3a83fd2fa38f05a053dfeefc3de71"},{"name":"Arrowhead Way","countries":"United States","regions":"Idaho","difficulty":"easy","color":"green","gladed":null,"grooming":null,"inclined_length_m":268,"descent_m":73,"ascent_m":0,"average_pitch_%":0.28,"max_pitch_%":0.34,"min_elevation_m":1932,"max_elevation_m":2004,"difficulty_convention":"north_america","openskimap":"https://openskimap.org/?obj=0a6b4ae8bf8ce98209d007ae32e07226c3d36e9b"},{"name":"Forbidden Fruit","countries":"United States","regions":"Idaho","difficulty":"easy","color":"green","gladed":null,"grooming":null,"inclined_length_m":872,"descent_m":150,"ascent_m":2,"average_pitch_%":0.18,"max_pitch_%":0.46,"min_elevation_m":1857,"max_elevation_m":2006,"difficulty_convention":"north_america","openskimap":"https://openskimap.org/?obj=100bb8b74e54f93e6f268e538102ae7ddb93212d"},{"name":"Trestles","countries":"United States","regions":"Idaho","difficulty":"easy","color":"green","gladed":null,"grooming":null,"inclined_length_m":234,"descent_m":45,"ascent_m":0,"average_pitch_%":0.2,"max_pitch_%":0.32,"min_elevation_m":1822,"max_elevation_m":1867,"difficulty_convention":"north_america","openskimap":"https://openskimap.org/?obj=1041bc6c78a78cbfa9abd30345ae87dde0466eb2"},{"name":"Sepp","countries":"United States","regions":"Idaho","difficulty":"easy","color":"green","gladed":null,"grooming":null,"inclined_length_m":503,"descent_m":112,"ascent_m":1,"average_pitch_%":0.23,"max_pitch_%":0.36,"min_elevation_m":1867,"max_elevation_m":1979,"difficulty_convention":"north_america","openskimap":"https://openskimap.org/?obj=1d00f8ea53a642453bf9b98620f6f0c0c1974da3"},{"name":"Upper Trestles","countries":"United States","regions":"Idaho","difficulty":"intermediate","color":"blue","gladed":null,"grooming":null,"inclined_length_m":351,"descent_m":96,"ascent_m":0,"average_pitch_%":0.28,"max_pitch_%":0.37,"min_elevation_m":1845,"max_elevation_m":1941,"difficulty_convention":"north_america","openskimap":"https://openskimap.org/?obj=2538c5ffb81af9556fe6c88c68d3cb437a2aea36"},{"name":"Elkhorn Bowl","countries":"United States","regions":"Idaho","difficulty":"easy","color":"green","gladed":null,"grooming":null,"inclined_length_m":1260,"descent_m":155,"ascent_m":0,"average_pitch_%":0.12,"max_pitch_%":0.26,"min_elevation_m":1849,"max_elevation_m":2004,"difficulty_convention":"north_america","openskimap":"https://openskimap.org/?obj=3b382901ae50cb27288c6fa3227b578db7929b88"},{"name":"Lombard Street","countries":"United States","regions":"Idaho","difficulty":"easy","color":"green","gladed":null,"grooming":null,"inclined_length_m":245,"descent_m":64,"ascent_m":0,"average_pitch_%":0.27,"max_pitch_%":0.36,"min_elevation_m":1918,"max_elevation_m":1982,"difficulty_convention":"north_america","openskimap":"https://openskimap.org/?obj=4f6b81032e5b01357a84ba3ab56b3169c57fb988"},{"name":"Dollar Face","countries":"United States","regions":"Idaho","difficulty":"intermediate","color":"blue","gladed":null,"grooming":null,"inclined_length_m":455,"descent_m":131,"ascent_m":0,"average_pitch_%":0.3,"max_pitch_%":0.44,"min_elevation_m":1848,"max_elevation_m":1979,"difficulty_convention":"north_america","openskimap":"https://openskimap.org/?obj=715231d44a1a73f2075aa9bb8166ff78572a2eb2"},{"name":"Mineshaft","countries":"United States","regions":"Idaho","difficulty":"intermediate","color":"blue","gladed":null,"grooming":null,"inclined_length_m":451,"descent_m":54,"ascent_m":0,"average_pitch_%":0.12,"max_pitch_%":0.27,"min_elevation_m":1815,"max_elevation_m":1869,"difficulty_convention":"north_america","openskimap":"https://openskimap.org/?obj=8d8937b9984aa3699e810e640efd5f912c8c0b50"},{"name":"Bitteroot Bowl","countries":"United States","regions":"Idaho","difficulty":"advanced","color":"black","gladed":null,"grooming":null,"inclined_length_m":1062,"descent_m":149,"ascent_m":9,"average_pitch_%":0.15,"max_pitch_%":0.58,"min_elevation_m":1837,"max_elevation_m":1984,"difficulty_convention":"north_america","openskimap":"https://openskimap.org/?obj=ad88058cc9b393eb94718f9902fd5c3655bffbaf"},{"name":"Joint Venture","countries":"United States","regions":"Idaho","difficulty":"easy","color":"green","gladed":null,"grooming":null,"inclined_length_m":781,"descent_m":168,"ascent_m":0,"average_pitch_%":0.22,"max_pitch_%":0.47,"min_elevation_m":1837,"max_elevation_m":2004,"difficulty_convention":"north_america","openskimap":"https://openskimap.org/?obj=b4304e1c6605452135723160059526007947f408"},{"name":"Cabin Practice","countries":"United States","regions":"Idaho","difficulty":"easy","color":"green","gladed":null,"grooming":null,"inclined_length_m":517,"descent_m":58,"ascent_m":1,"average_pitch_%":0.12,"max_pitch_%":0.21,"min_elevation_m":1815,"max_elevation_m":1871,"difficulty_convention":"north_america","openskimap":"https://openskimap.org/?obj=b8195ef388971f3cf4f6b167a77cd478fd78d7f9"},{"name":"Prospector Park","countries":"United States","regions":"Idaho","difficulty":"easy","color":"green","gladed":null,"grooming":null,"inclined_length_m":352,"descent_m":36,"ascent_m":0,"average_pitch_%":0.1,"max_pitch_%":0.14,"min_elevation_m":1827,"max_elevation_m":1863,"difficulty_convention":"north_america","openskimap":"https://openskimap.org/?obj=b9fbf290ad88e805d17da4ceaa5ca0a605e91197"},{"name":"Elhorn Face","countries":"United States","regions":"Idaho","difficulty":"intermediate","color":"blue","gladed":null,"grooming":null,"inclined_length_m":424,"descent_m":124,"ascent_m":0,"average_pitch_%":0.31,"max_pitch_%":0.45,"min_elevation_m":1870,"max_elevation_m":1994,"difficulty_convention":"north_america","openskimap":"https://openskimap.org/?obj=ba9ebb3e67ea03dbcd311a8f5515c9acc4223b6a"},{"name":"New Bowl","countries":"United States","regions":"Idaho","difficulty":"intermediate","color":"blue","gladed":null,"grooming":null,"inclined_length_m":856,"descent_m":190,"ascent_m":0,"average_pitch_%":0.23,"max_pitch_%":0.44,"min_elevation_m":1816,"max_elevation_m":2006,"difficulty_convention":"north_america","openskimap":"https://openskimap.org/?obj=bd5e059c4be537f310dda3edd0724b041c295032"},{"name":"Graduation","countries":"United States","regions":"Idaho","difficulty":"easy","color":"green","gladed":null,"grooming":null,"inclined_length_m":305,"descent_m":55,"ascent_m":0,"average_pitch_%":0.18,"max_pitch_%":0.29,"min_elevation_m":1816,"max_elevation_m":1871,"difficulty_convention":"north_america","openskimap":"https://openskimap.org/?obj=c4450fc88f9fcf7a7b355b760d6958a644ec0e62"},{"name":"Old Bowl","countries":"United States","regions":"Idaho","difficulty":"intermediate","color":"blue","gladed":null,"grooming":null,"inclined_length_m":388,"descent_m":70,"ascent_m":5,"average_pitch_%":0.2,"max_pitch_%":0.39,"min_elevation_m":1941,"max_elevation_m":2007,"difficulty_convention":"north_america","openskimap":"https://openskimap.org/?obj=d36bfca9e705258aba9da534d423b91bde4699e2"},{"name":"Otto's Run","countries":"United States","regions":"Idaho","difficulty":"intermediate","color":"blue","gladed":null,"grooming":null,"inclined_length_m":323,"descent_m":73,"ascent_m":0,"average_pitch_%":0.23,"max_pitch_%":0.45,"min_elevation_m":1908,"max_elevation_m":1981,"difficulty_convention":"north_america","openskimap":"https://openskimap.org/?obj=d9116fa258ae4c4ce92cf71a6b3a3fe4091b8756"},{"name":"Poverty Flats","countries":"United States","regions":"Idaho","difficulty":"easy","color":"green","gladed":null,"grooming":null,"inclined_length_m":545,"descent_m":53,"ascent_m":0,"average_pitch_%":0.1,"max_pitch_%":0.14,"min_elevation_m":1814,"max_elevation_m":1867,"difficulty_convention":"north_america","openskimap":"https://openskimap.org/?obj=e53d9bb7f3a6494654b7046ec1fbcd8fb53741a8"},{"name":"Motherlode","countries":"United States","regions":"Idaho","difficulty":"easy","color":"green","gladed":null,"grooming":null,"inclined_length_m":353,"descent_m":55,"ascent_m":0,"average_pitch_%":0.16,"max_pitch_%":0.33,"min_elevation_m":1814,"max_elevation_m":1869,"difficulty_convention":"north_america","openskimap":"https://openskimap.org/?obj=e9c14da455e52aea22d1ee2c86d504d0638b0586"},{"name":"Dragon's Back","countries":"United States","regions":"Idaho","difficulty":"advanced","color":"black","gladed":null,"grooming":"mogul","inclined_length_m":380,"descent_m":123,"ascent_m":0,"average_pitch_%":0.34,"max_pitch_%":0.49,"min_elevation_m":1863,"max_elevation_m":1986,"difficulty_convention":"north_america","openskimap":"https://openskimap.org/?obj=fbb9323581aab206b025cce6f0261ac85691ca3a"}]